tests/__init__.py
tests/test_datasets.py
tests/test_eeg_utils.py
tests/test_nbs_utils.py
tests/test_pairwise_tfns.py
tests/test_tfnos.py
tests/test_utils.py
tfnbs/__init__.py
tfnbs/datasets.py
tfnbs/eeg_utils.py
tfnbs/nbs_utils.py
tfnbs/pairwise_tfns.py
tfnbs/tfnos.py
tfnbs/utils.py
tfnbs-1.0.0.dist-info/licenses/LICENSE
tfnbs-1.0.0.dist-info/METADATA
tfnbs-1.0.0.dist-info/WHEEL
tfnbs-1.0.0.dist-info/top_level.txt
tfnbs-1.0.0.dist-info/RECORD
