Metadata-Version: 2.4
Name: TFNBS
Version: 1.0.0
Summary: Threshold Free Network Based Statistics (TFNBS) Toolkit
Home-page: https://github.com/IHB-IBR-department/TFNBS
Author: N.P. Bechtereva Institute of the Human Brain, Russian Academy of Sciences
Author-email: ashish@ireddy.ru
License: MIT
Classifier: Programming Language :: Python :: 3
Requires-Python: >=3.8
License-File: LICENSE
Requires-Dist: numpy
Requires-Dist: scipy
Requires-Dist: matplotlib
Requires-Dist: scikit-learn
Requires-Dist: networkx
Requires-Dist: mne
Requires-Dist: pandas
Provides-Extra: dev
Requires-Dist: pytest; extra == "dev"
Requires-Dist: sphinx; extra == "dev"
Requires-Dist: sphinx-rtd-theme; extra == "dev"
Dynamic: license-file
